tests/__init__.py
tests/test_aes.py
tests/test_des.py
tests/test_import.py
tests/test_pbkdf2.py
tests/test_rc4.py
tests/test_tdes.py
unicrypto/__init__.py
unicrypto/_version.py
unicrypto/cmac.py
unicrypto/hashlib.py
unicrypto/hmac.py
unicrypto/kdf.py
unicrypto/pbkdf2.py
unicrypto/symmetric.py
unicrypto/backends/__init__.py
unicrypto/backends/cmac.py
unicrypto/backends/kdf.py
unicrypto/backends/cryptography/AES.py
unicrypto/backends/cryptography/DES.py
unicrypto/backends/cryptography/RC4.py
unicrypto/backends/cryptography/TDES.py
unicrypto/backends/cryptography/__init__.py
unicrypto/backends/mbedtls/AES.py
unicrypto/backends/mbedtls/DES.py
unicrypto/backends/mbedtls/RC4.py
unicrypto/backends/mbedtls/TDES.py
unicrypto/backends/mbedtls/__init__.py
unicrypto/backends/pure/AES.py
unicrypto/backends/pure/DES.py
unicrypto/backends/pure/MD4.py
unicrypto/backends/pure/RC4.py
unicrypto/backends/pure/TDES.py
unicrypto/backends/pure/__init__.py
unicrypto/backends/pure/external/__init__.py
unicrypto/backends/pure/external/AES/AES.py
unicrypto/backends/pure/external/AES/AESCCM.py
unicrypto/backends/pure/external/AES/AESGCM.py
unicrypto/backends/pure/external/AES/__init__.py
unicrypto/backends/pure/external/AES/blockfeeder.py
unicrypto/backends/pure/external/AES/ccm.py
unicrypto/backends/pure/external/AES/gcc_bak_orig.py
unicrypto/backends/pure/external/AES/util.py
unicrypto/backends/pure/external/DES/DES.py
unicrypto/backends/pure/external/DES/__init__.py
unicrypto/backends/pure/external/RC4/RC4.py
unicrypto/backends/pure/external/RC4/__init__.py
unicrypto/backends/pure/padding/__init__.py
unicrypto/backends/pure/padding/pkcs7.py
unicrypto/backends/pycrypto/AES.py
unicrypto/backends/pycrypto/DES.py
unicrypto/backends/pycrypto/RC4.py
unicrypto/backends/pycrypto/TDES.py
unicrypto/backends/pycrypto/__init__.py
unicrypto/backends/pycrypto/extra/AESGCM.py
unicrypto/backends/pycrypto/extra/__init__.py
unicrypto/backends/pycryptodome/AES.py
unicrypto/backends/pycryptodome/DES.py
unicrypto-0.0.11.dist-info/LICENSE
unicrypto-0.0.11.dist-info/METADATA
unicrypto-0.0.11.dist-info/WHEEL
unicrypto-0.0.11.dist-info/top_level.txt
unicrypto-0.0.11.dist-info/zip-safe
unicrypto-0.0.11.dist-info/RECORD
